mcaapi/APItoken.py
mcaapi/__init__.py
mcaapi/inputs.py
mcaapi/mcaapi.py
mcaapi/tests.py
mcaapi/datasets/__init__.py
mcaapi/datasets/residential_10k.csv
mcaapi/datasets/residential_10k.rst
mcaapi-0.1.3.dist-info/METADATA
mcaapi-0.1.3.dist-info/WHEEL
mcaapi-0.1.3.dist-info/top_level.txt
mcaapi-0.1.3.dist-info/RECORD
