Metadata-Version: 2.1
Name: mcaapi
Version: 0.1.3
Summary: A Python wrapper for the Maricopa County Assessor API.
Home-page: https://mcaapi.readthedocs.io
Author: FoxbatCS
Author-email: fbcs@foxbatcs.com
License: MIT
Project-URL: repository, https://github.com/foxbatcs/mcaapi
Platform: UNKNOWN
Requires-Python: ==3.*
Provides-Extra: dev
Requires-Dist: wheel (==0.*,>=0.30.0) ; extra == 'dev'
